[{"sid": "C06", "name": "Uimastadion", "weekday": 0, "hour": 1, "label": "Monday", "rain_bike_brought": 686.1966588175612, "no_rain_bike_brought": 167.51843568819604, "warm_bike_brought": 153.01385024904906, "cold_bike_brought": 171.21559772494425, "rain_bike_taken": 812.3898010154016, "no_rain_bike_taken": 258.00179091199664, "warm_bike_taken": 239.65807695705038, "cold_bike_taken": 263.2170482270853, "rain_limit": 0.2, "temp_limit": 20}, {"sid": "C06", "name": "Uimastadion", "weekday": 0, "hour": 2, "label": "Monday", "rain_bike_brought": 731.841071376239, "no_rain_bike_brought": 146.91293687988087, "warm_bike_brought": 68.71964727777707, "cold_bike_brought": 151.2548639488417, "rain_bike_taken": 802.6597176969075, "no_rain_bike_taken": 200.01828155954956, "warm_bike_taken": 157.65584357982863, "cold_bike_taken": 202.5406170263831, "rain_limit": 0.2, "temp_limit": 20}, {"sid": "C06", "name": "Uimastadion", "weekday": 0, "hour": 3, "label": "Monday", "rain_bike_brought": 83.75235876613736, "no_rain_bike_brought": 28.528095495813275, "warm_bike_brought": 12.283435078835064, "cold_bike_brought": 32.906029603814694, "rain_bike_taken": 94.93854165467813, "no_rain_bike_taken": 159.17599472009422, "warm_bike_taken": 76.33959098077007, "cold_bike_taken": 166.9917703730344, "rain_limit": 0.2, "temp_limit": 20}, {"sid": "C06", "name": "Uimastadion", "weekday": 0, "hour": 4, "label": "Monday", "rain_bike_brought": 119.46810032366666, "no_rain_bike_brought": 41.14911837849493, "warm_bike_brought": 29.251553952935716, "cold_bike_brought": 49.7026219062685, "rain_bike_taken": 172.12103466335512, "no_rain_bike_taken": 39.74957531870795, "warm_bike_taken": 20.034944264524963, "cold_bike_taken": 49.69560231320825, "rain_limit": 0.2, "temp_limit": 20}, {"sid": "C06", "name": "Uimastadion", "weekday": 0, "hour": 5, "label": "Monday", "rain_bike_brought": 76.34433738044146, "no_rain_bike_brought": 42.64099965166246, "warm_bike_brought": 15.893330563749897, "cold_bike_brought": 51.862576237601914, "rain_bike_taken": 184.0614202366845, "no_rain_bike_taken": 25.963915509936474, "warm_bike_taken": 17.075550373442322, "cold_bike_taken": 30.653054509160462, "rain_limit": 0.2, "temp_limit": 20}, {"sid": "C06", "name": "Uimastadion", "weekday": 0, "hour": 6, "label": "Monday", "rain_bike_brought": 224.3702597475972, "no_rain_bike_brought": 56.93333436571892, "warm_bike_brought": 18.491661469504425, "cold_bike_brought": 75.76835381396933, "rain_bike_taken": 93.81029194645646, "no_rain_bike_taken": 61.12772263354391, "warm_bike_taken": 19.1622799514468, "cold_bike_taken": 78.75759173808079, "rain_limit": 0.2, "temp_limit": 20}, {"sid": "C06", "name": "Uimastadion", "weekday": 0, "hour": 7, "label": "Monday", "rain_bike_brought": 224.54440390104688, "no_rain_bike_brought": 51.36594396935548, "warm_bike_brought": 13.742065434613352, "cold_bike_brought": 69.41418828794764, "rain_bike_taken": 44.5238040538058, "no_rain_bike_taken": 53.08417363653058, "warm_bike_taken": 23.840331785596454, "cold_bike_taken": 62.59815054268998, "rain_limit": 0.2, "temp_limit": 20}, {"sid": "C06", "name": "Uimastadion", "weekday": 0, "hour": 8, "label": "Monday", "rain_bike_brought": 180.68168320202005, "no_rain_bike_brought": 34.61662022214796, "warm_bike_brought": 7.430611950180494, "cold_bike_brought": 50.726737409345965, "rain_bike_taken": 189.96757628852268, "no_rain_bike_taken": 51.55181695883663, "warm_bike_taken": 13.871189471476276, "cold_bike_taken": 74.41185303931816, "rain_limit": 0.2, "temp_limit": 20}, {"sid": "C06", "name": "Uimastadion", "weekday": 0, "hour": 9, "label": "Monday", "rain_bike_brought": 113.58956652700569, "no_rain_bike_brought": 28.310971790186816, "warm_bike_brought": 10.035781889100988, "cold_bike_brought": 65.20639856234234, "rain_bike_taken": 161.6775193822393, "no_rain_bike_taken": 30.032574836718975, "warm_bike_taken": 15.930085294360055, "cold_bike_taken": 59.28421719997749, "rain_limit": 0.2, "temp_limit": 20}, {"sid": "C06", "name": "Uimastadion", "weekday": 0, "hour": 10, "label": "Monday", "rain_bike_brought": 81.59961393426202, "no_rain_bike_brought": 27.189326331084214, "warm_bike_brought": 13.987400883600168, "cold_bike_brought": 47.71418854209444, "rain_bike_taken": 75.66443113787047, "no_rain_bike_taken": 30.94819653569903, "warm_bike_taken": 14.399401717966981, "cold_bike_taken": 67.31853955188629, "rain_limit": 0.2, "temp_limit": 20}, {"sid": "C06", "name": "Uimastadion", "weekday": 0, "hour": 11, "label": "Monday", "rain_bike_brought": 24.3545122183809, "no_rain_bike_brought": 34.671825491804874, "warm_bike_brought": 13.322561910619681, "cold_bike_brought": 62.26327652008615, "rain_bike_taken": 23.081274956321224, "no_rain_bike_taken": 31.56956235983303, "warm_bike_taken": 15.177063944755997, "cold_bike_taken": 56.65538787413927, "rain_limit": 0.2, "temp_limit": 20}, {"sid": "C06", "name": "Uimastadion", "weekday": 0, "hour": 12, "label": "Monday", "rain_bike_brought": 92.91769438505436, "no_rain_bike_brought": 24.99177434482706, "warm_bike_brought": 16.89823306150714, "cold_bike_brought": 35.26476761199919, "rain_bike_taken": 129.53151545899394, "no_rain_bike_taken": 34.187266610898725, "warm_bike_taken": 13.66167598577308, "cold_bike_taken": 63.18210283208485, "rain_limit": 0.2, "temp_limit": 20}, {"sid": "C06", "name": "Uimastadion", "weekday": 0, "hour": 13, "label": "Monday", "rain_bike_brought": 68.21393053336713, "no_rain_bike_brought": 20.611608027249904, "warm_bike_brought": 7.837691865070412, "cold_bike_brought": 30.71293103535428, "rain_bike_taken": 164.3453984776132, "no_rain_bike_taken": 19.16925407456141, "warm_bike_taken": 9.906060582983343, "cold_bike_taken": 32.348745853374815, "rain_limit": 0.2, "temp_limit": 20}, {"sid": "C06", "name": "Uimastadion", "weekday": 0, "hour": 14, "label": "Monday", "rain_bike_brought": 30.40462188795839, "no_rain_bike_brought": 16.495345108341944, "warm_bike_brought": 6.3108577527824306, "cold_bike_brought": 22.81907709781973, "rain_bike_taken": 94.23133658733835, "no_rain_bike_taken": 20.647975841662607, "warm_bike_taken": 6.836494077832518, "cold_bike_taken": 32.512198624283386, "rain_limit": 0.2, "temp_limit": 20}, {"sid": "C06", "name": "Uimastadion", "weekday": 0, "hour": 15, "label": "Monday", "rain_bike_brought": 55.69702816485748, "no_rain_bike_brought": 11.012783016286168, "warm_bike_brought": 6.049836458195191, "cold_bike_brought": 18.316815908536864, "rain_bike_taken": 27.70457768549919, "no_rain_bike_taken": 11.062179199376295, "warm_bike_taken": 5.287380023914326, "cold_bike_taken": 19.561662552115976, "rain_limit": 0.2, "temp_limit": 20}, {"sid": "C06", "name": "Uimastadion", "weekday": 0, "hour": 16, "label": "Monday", "rain_bike_brought": 53.50386525400334, "no_rain_bike_brought": 17.34039187651716, "warm_bike_brought": 15.353232609481084, "cold_bike_brought": 20.42336042602474, "rain_bike_taken": 58.650751524269694, "no_rain_bike_taken": 11.869866330665474, "warm_bike_taken": 9.009296641624095, "cold_bike_taken": 15.927953009104725, "rain_limit": 0.2, "temp_limit": 20}, {"sid": "C06", "name": "Uimastadion", "weekday": 0, "hour": 17, "label": "Monday", "rain_bike_brought": 1040.1737314294446, "no_rain_bike_brought": 144.86428832423968, "warm_bike_brought": 28.829876461048794, "cold_bike_brought": 423.8657604608935, "rain_bike_taken": 77.16274875309118, "no_rain_bike_taken": 31.24001988588852, "warm_bike_taken": 28.330836334381402, "cold_bike_taken": 34.59907367269206, "rain_limit": 0.2, "temp_limit": 20}, {"sid": "C06", "name": "Uimastadion", "weekday": 0, "hour": 18, "label": "Monday", "rain_bike_brought": 1131.845207739824, "no_rain_bike_brought": 660.5678220148047, "warm_bike_brought": 56.24050616648265, "cold_bike_brought": 1003.5104354285545, "rain_bike_taken": 965.2571600336345, "no_rain_bike_taken": 223.22712711161515, "warm_bike_taken": 47.19864238737855, "cold_bike_taken": 781.5648694019601, "rain_limit": 0.2, "temp_limit": 20}, {"sid": "C06", "name": "Uimastadion", "weekday": 0, "hour": 19, "label": "Monday", "rain_bike_brought": 1199.2372173214183, "no_rain_bike_brought": 1407.1253338330505, "warm_bike_brought": 1189.4406314545097, "cold_bike_brought": 1399.8687774446566, "rain_bike_taken": 1182.8257892987763, "no_rain_bike_taken": 1190.1398997788992, "warm_bike_taken": 129.80837804752676, "cold_bike_taken": 1210.3531447834532, "rain_limit": 0.2, "temp_limit": 20}, {"sid": "C06", "name": "Uimastadion", "weekday": 0, "hour": 20, "label": "Monday", "rain_bike_brought": 1371.6068314583988, "no_rain_bike_brought": 1486.2311445200023, "warm_bike_brought": 1426.6624267914042, "cold_bike_brought": 1488.843328844137, "rain_bike_taken": 229.21649147684363, "no_rain_bike_taken": 1453.5716374523254, "warm_bike_taken": 1344.2232954341303, "cold_bike_taken": 1358.5437690128988, "rain_limit": 0.2, "temp_limit": 20}, {"sid": "C06", "name": "Uimastadion", "weekday": 0, "hour": 21, "label": "Monday", "rain_bike_brought": 1261.6533798168978, "no_rain_bike_brought": 1497.780223747254, "warm_bike_brought": 1509.8343494827873, "cold_bike_brought": 1457.341575519158, "rain_bike_taken": 1267.2001471781625, "no_rain_bike_taken": 1426.6879854226963, "warm_bike_taken": 1427.642462630304, "cold_bike_taken": 1385.1744109311883, "rain_limit": 0.2, "temp_limit": 20}, {"sid": "C06", "name": "Uimastadion", "weekday": 0, "hour": 22, "label": "Monday", "rain_bike_brought": 1541.931783742011, "no_rain_bike_brought": 1545.3246551469929, "warm_bike_brought": 1591.9851464882624, "cold_bike_brought": 1524.635821840168, "rain_bike_taken": 1504.4622982247295, "no_rain_bike_taken": 1512.5891503939135, "warm_bike_taken": 1514.258540884629, "cold_bike_taken": 1496.1359450881791, "rain_limit": 0.2, "temp_limit": 20}, {"sid": "C06", "name": "Uimastadion", "weekday": 0, "hour": 23, "label": "Monday", "rain_bike_brought": 1431.7105009573538, "no_rain_bike_brought": 1596.5899782246584, "warm_bike_brought": 1674.0517267396792, "cold_bike_brought": 1574.5011812362989, "rain_bike_taken": 1437.2887191327702, "no_rain_bike_taken": 1559.514360740797, "warm_bike_taken": 1596.147172428439, "cold_bike_taken": 1546.860424430803, "rain_limit": 0.2, "temp_limit": 20}, {"sid": "C06", "name": "Uimastadion", "weekday": 1, "hour": 0, "label": "Tuesday", "rain_bike_brought": 285.7844955528843, "no_rain_bike_brought": 250.42508976324189, "warm_bike_brought": 237.3293912537803, "cold_bike_brought": 252.65540886748767, "rain_bike_taken": 323.3493111960724, "no_rain_bike_taken": 367.6461344378295, "warm_bike_taken": 314.3459906554852, "cold_bike_taken": 369.6970195252908, "rain_limit": 0.2, "temp_limit": 20}, {"sid": "C06", "name": "Uimastadion", "weekday": 1, "hour": 2, "label": "Tuesday", "rain_bike_brought": 321.9615492751473, "no_rain_bike_brought": 134.82337010058606, "warm_bike_brought": 70.02222261486153, "cold_bike_brought": 137.66685430829475, "rain_bike_taken": 316.38572791768416, "no_rain_bike_taken": 213.89759692502395, "warm_bike_taken": 144.60222888150392, "cold_bike_taken": 218.6460487831301, "rain_limit": 0.2, "temp_limit": 20}, {"sid": "C06", "name": "Uimastadion", "weekday": 1, "hour": 3, "label": "Tuesday", "rain_bike_brought": 170.877451642204, "no_rain_bike_brought": 18.170834028997778, "warm_bike_brought": 10.669321264274542, "cold_bike_brought": 20.939442341113242, "rain_bike_taken": 230.0164373921556, "no_rain_bike_taken": 141.10864137560208, "warm_bike_taken": 77.03679963322793, "cold_bike_taken": 154.04432116861747, "rain_limit": 0.2, "temp_limit": 20}, {"sid": "C06", "name": "Uimastadion", "weekday": 1, "hour": 4, "label": "Tuesday", "rain_bike_brought": 200.35554734803705, "no_rain_bike_brought": 17.589271437461022, "warm_bike_brought": 7.27311831812661, "cold_bike_brought": 22.839718656446923, "rain_bike_taken": 214.44466015036994, "no_rain_bike_taken": 24.97407579539538, "warm_bike_taken": 12.05880286541555, "cold_bike_taken": 31.595456401086217, "rain_limit": 0.2, "temp_limit": 20}, {"sid": "C06", "name": "Uimastadion", "weekday": 1, "hour": 5, "label": "Tuesday", "rain_bike_brought": 154.9442073350966, "no_rain_bike_brought": 39.766221002926684, "warm_bike_brought": 10.371709315754401, "cold_bike_brought": 54.970433860113644, "rain_bike_taken": 92.31828514135594, "no_rain_bike_taken": 19.723543204922823, "warm_bike_taken": 8.268958344638603, "cold_bike_taken": 24.013655961487085, "rain_limit": 0.2, "temp_limit": 20}, {"sid": "C06", "name": "Uimastadion", "weekday": 1, "hour": 6, "label": "Tuesday", "rain_bike_brought": 66.96292512394812, "no_rain_bike_brought": 37.17329332923346, "warm_bike_brought": 22.090106858668722, "cold_bike_brought": 43.96211457590713, "rain_bike_taken": 82.73162319270439, "no_rain_bike_taken": 29.165453750837198, "warm_bike_taken": 10.189329719624233, "cold_bike_taken": 39.87039446402049, "rain_limit": 0.2, "temp_limit": 20}, {"sid": "C06", "name": "Uimastadion", "weekday": 1, "hour": 7, "label": "Tuesday", "rain_bike_brought": 553.0835451965763, "no_rain_bike_brought": 33.34563689987044, "warm_bike_brought": 13.912201229653354, "cold_bike_brought": 50.07678943957314, "rain_bike_taken": 300.1019378977871, "no_rain_bike_taken": 39.47722930339576, "warm_bike_taken": 18.415593640637567, "cold_bike_taken": 55.661212387625675, "rain_limit": 0.2, "temp_limit": 20}, {"sid": "C06", "name": "Uimastadion", "weekday": 1, "hour": 8, "label": "Tuesday", "rain_bike_brought": 466.0157997397434, "no_rain_bike_brought": 38.71286859349387, "warm_bike_brought": 10.58296318610224, "cold_bike_brought": 77.67856704992998, "rain_bike_taken": 212.51117095047817, "no_rain_bike_taken": 36.781928929691766, "warm_bike_taken": 21.82951856058519, "cold_bike_taken": 55.135237034089016, "rain_limit": 0.2, "temp_limit": 20}, {"sid": "C06", "name": "Uimastadion", "weekday": 1, "hour": 9, "label": "Tuesday", "rain_bike_brought": 76.81167812166314, "no_rain_bike_brought": 32.92217452631784, "warm_bike_brought": 9.920180258327031, "cold_bike_brought": 69.13618651254492, "rain_bike_taken": 51.795798343973956, "no_rain_bike_taken": 40.33867071358697, "warm_bike_taken": 14.40789576798888, "cold_bike_taken": 65.44834673783099, "rain_limit": 0.2, "temp_limit": 20}, {"sid": "C06", "name": "Uimastadion", "weekday": 1, "hour": 10, "label": "Tuesday", "rain_bike_brought": 185.6538452968879, "no_rain_bike_brought": 31.95488204191159, "warm_bike_brought": 13.886129732581349, "cold_bike_brought": 67.99068928270663, "rain_bike_taken": 99.33323330194078, "no_rain_bike_taken": 32.44309310755436, "warm_bike_taken": 12.800951949322414, "cold_bike_taken": 71.77848052582236, "rain_limit": 0.2, "temp_limit": 20}, {"sid": "C06", "name": "Uimastadion", "weekday": 1, "hour": 11, "label": "Tuesday", "rain_bike_brought": 247.45005063017408, "no_rain_bike_brought": 28.924635386597128, "warm_bike_brought": 11.619405681078094, "cold_bike_brought": 52.2285988067106, "rain_bike_taken": 41.79719394503034, "no_rain_bike_taken": 32.89634703455496, "warm_bike_taken": 9.879694764340405, "cold_bike_taken": 69.69689836158987, "rain_limit": 0.2, "temp_limit": 20}, {"sid": "C06", "name": "Uimastadion", "weekday": 1, "hour": 12, "label": "Tuesday", "rain_bike_brought": 202.95988724499605, "no_rain_bike_brought": 18.952925429420127, "warm_bike_brought": 10.411261187369089, "cold_bike_brought": 29.407196817465458, "rain_bike_taken": 75.19299243547484, "no_rain_bike_taken": 26.261143160982243, "warm_bike_taken": 7.911331037963004, "cold_bike_taken": 51.0723351454348, "rain_limit": 0.2, "temp_limit": 20}, {"sid": "C06", "name": "Uimastadion", "weekday": 1, "hour": 13, "label": "Tuesday", "rain_bike_brought": 150.64386824726975, "no_rain_bike_brought": 11.911838416845272, "warm_bike_brought": 7.463363037081027, "cold_bike_brought": 20.744892275479913, "rain_bike_taken": 176.70284344099093, "no_rain_bike_taken": 14.691906413508741, "warm_bike_taken": 7.730438224938289, "cold_bike_taken": 30.841001688354424, "rain_limit": 0.2, "temp_limit": 20}, {"sid": "C06", "name": "Uimastadion", "weekday": 1, "hour": 14, "label": "Tuesday", "rain_bike_brought": 133.32617214480925, "no_rain_bike_brought": 8.140161482351925, "warm_bike_brought": 5.163518176632575, "cold_bike_brought": 12.114414037218744, "rain_bike_taken": 261.65678000752666, "no_rain_bike_taken": 12.085147932816849, "warm_bike_taken": 6.818737097426173, "cold_bike_taken": 19.42754012764245, "rain_limit": 0.2, "temp_limit": 20}, {"sid": "C06", "name": "Uimastadion", "weekday": 1, "hour": 15, "label": "Tuesday", "rain_bike_brought": 325.99312710299824, "no_rain_bike_brought": 17.888831404114434, "warm_bike_brought": 6.857768836661237, "cold_bike_brought": 26.04714536558651, "rain_bike_taken": 182.59324837161225, "no_rain_bike_taken": 9.904775347475244, "warm_bike_taken": 6.356730245665286, "cold_bike_taken": 22.421928117933984, "rain_limit": 0.2, "temp_limit": 20}, {"sid": "C06", "name": "Uimastadion", "weekday": 1, "hour": 16, "label": "Tuesday", "rain_bike_brought": 102.0318257731523, "no_rain_bike_brought": 18.002203638866057, "warm_bike_brought": 10.95638677907567, "cold_bike_brought": 24.86089424521166, "rain_bike_taken": 21.906157785037315, "no_rain_bike_taken": 11.463185154706707, "warm_bike_taken": 6.347469321029502, "cold_bike_taken": 14.631935980765792, "rain_limit": 0.2, "temp_limit": 20}, {"sid": "C06", "name": "Uimastadion", "weekday": 1, "hour": 17, "label": "Tuesday", "rain_bike_brought": 184.1358229441113, "no_rain_bike_brought": 66.46146177362408, "warm_bike_brought": 41.69627709240497, "cold_bike_brought": 95.54203225757561, "rain_bike_taken": 37.29284972546659, "no_rain_bike_taken": 37.818073844573, "warm_bike_taken": 36.5292372375692, "cold_bike_taken": 38.53072908293829, "rain_limit": 0.2, "temp_limit": 20}, {"sid": "C06", "name": "Uimastadion", "weekday": 1, "hour": 18, "label": "Tuesday", "rain_bike_brought": 114.04275910320433, "no_rain_bike_brought": 696.0304748365719, "warm_bike_brought": 145.50998311505415, "cold_bike_brought": 611.1278504492778, "rain_bike_taken": 578.5350187488527, "no_rain_bike_taken": 544.4917420909604, "warm_bike_taken": 127.90565975431377, "cold_bike_taken": 600.5670168769692, "rain_limit": 0.2, "temp_limit": 20}, {"sid": "C06", "name": "Uimastadion", "weekday": 1, "hour": 19, "label": "Tuesday", "rain_bike_brought": 392.82270161066924, "no_rain_bike_brought": 1220.7952870447843, "warm_bike_brought": 195.06853171130194, "cold_bike_brought": 1224.026094965247, "rain_bike_taken": 859.0452246074902, "no_rain_bike_taken": 1108.8510242909326, "warm_bike_taken": 250.14553605773045, "cold_bike_taken": 1192.7617600087615, "rain_limit": 0.2, "temp_limit": 20}, {"sid": "C06", "name": "Uimastadion", "weekday": 1, "hour": 20, "label": "Tuesday", "rain_bike_brought": 835.3102666155663, "no_rain_bike_brought": 1425.4922008243311, "warm_bike_brought": 284.45623187660976, "cold_bike_brought": 1421.3087198532953, "rain_bike_taken": 1104.5981240495453, "no_rain_bike_taken": 1343.3412029819242, "warm_bike_taken": 309.45969628092746, "cold_bike_taken": 1375.8499573994961, "rain_limit": 0.2, "temp_limit": 20}, {"sid": "C06", "name": "Uimastadion", "weekday": 1, "hour": 21, "label": "Tuesday", "rain_bike_brought": 727.7255274984365, "no_rain_bike_brought": 1504.0814131680559, "warm_bike_brought": 369.4568021889505, "cold_bike_brought": 1480.201301007152, "rain_bike_taken": 1095.2575277985884, "no_rain_bike_taken": 1430.478379314403, "warm_bike_taken": 216.06864145435694, "cold_bike_taken": 1410.9094391724302, "rain_limit": 0.2, "temp_limit": 20}, {"sid": "C06", "name": "Uimastadion", "weekday": 1, "hour": 22, "label": "Tuesday", "rain_bike_brought": 917.5313018375451, "no_rain_bike_brought": 1523.3608387071833, "warm_bike_brought": 1605.9208940176575, "cold_bike_brought": 1472.1900340720472, "rain_bike_taken": 1216.6356326647754, "no_rain_bike_taken": 1476.7485559614165, "warm_bike_taken": 1499.3352313591117, "cold_bike_taken": 1434.2139331174535, "rain_limit": 0.2, "temp_limit": 20}, {"sid": "C06", "name": "Uimastadion", "weekday": 1, "hour": 23, "label": "Tuesday", "rain_bike_brought": 619.6765883381684, "no_rain_bike_brought": 1638.7974585174686, "warm_bike_brought": 1688.2177276035193, "cold_bike_brought": 1600.5336317361252, "rain_bike_taken": 990.1590690944793, "no_rain_bike_taken": 1577.2103628461848, "warm_bike_taken": 1581.6696903638133, "cold_bike_taken": 1548.164705979377, "rain_limit": 0.2, "temp_limit": 20}, {"sid": "C06", "name": "Uimastadion", "weekday": 2, "hour": 0, "label": "Wednesdy", "rain_bike_brought": 251.12293294662655, "no_rain_bike_brought": 245.19968567473765, "warm_bike_brought": 224.47048497615356, "cold_bike_brought": 247.6461221471196, "rain_bike_taken": 370.78120074401136, "no_rain_bike_taken": 335.1920687053091, "warm_bike_taken": 329.883542774534, "cold_bike_taken": 336.8059717485653, "rain_limit": 0.2, "temp_limit": 20}, {"sid": "C06", "name": "Uimastadion", "weekday": 2, "hour": 1, "label": "Wednesdy", "rain_bike_brought": 143.25737836849694, "no_rain_bike_brought": 163.1247721524067, "warm_bike_brought": 152.41425925335844, "cold_bike_brought": 163.30415510264717, "rain_bike_taken": 263.26709472841725, "no_rain_bike_taken": 250.89506631920577, "warm_bike_taken": 256.03335775718426, "cold_bike_taken": 250.51301659256248, "rain_limit": 0.2, "temp_limit": 20}, {"sid": "C06", "name": "Uimastadion", "weekday": 2, "hour": 2, "label": "Wednesdy", "rain_bike_brought": 875.8579946158634, "no_rain_bike_brought": 130.5228233574514, "warm_bike_brought": 95.13473464601438, "cold_bike_brought": 138.28099188231883, "rain_bike_taken": 724.5798116846415, "no_rain_bike_taken": 192.61820362756507, "warm_bike_taken": 160.60759702426952, "cold_bike_taken": 196.55855503400778, "rain_limit": 0.2, "temp_limit": 20}, {"sid": "C06", "name": "Uimastadion", "weekday": 2, "hour": 3, "label": "Wednesdy", "rain_bike_brought": 167.00407334552486, "no_rain_bike_brought": 20.028626242531207, "warm_bike_brought": 9.801234583249837, "cold_bike_brought": 24.25224869948527, "rain_bike_taken": 432.66066309745906, "no_rain_bike_taken": 148.96149960267388, "warm_bike_taken": 87.15260698687892, "cold_bike_taken": 160.53497211819266, "rain_limit": 0.2, "temp_limit": 20}, {"sid": "C06", "name": "Uimastadion", "weekday": 2, "hour": 4, "label": "Wednesdy", "rain_bike_brought": 36.10328474741872, "no_rain_bike_brought": 21.561799042598455, "warm_bike_brought": 8.72615892547088, "cold_bike_brought": 24.54468136335627, "rain_bike_taken": 127.93084534414155, "no_rain_bike_taken": 26.86201394884526, "warm_bike_taken": 16.967672041461164, "cold_bike_taken": 29.88654037195008, "rain_limit": 0.2, "temp_limit": 20}, {"sid": "C06", "name": "Uimastadion", "weekday": 2, "hour": 5, "label": "Wednesdy", "rain_bike_brought": 338.94369005602374, "no_rain_bike_brought": 30.290298506996372, "warm_bike_brought": 19.27108337526149, "cold_bike_brought": 36.32275034543903, "rain_bike_taken": 159.653643605226, "no_rain_bike_taken": 14.960251398440331, "warm_bike_taken": 8.187906972714673, "cold_bike_taken": 18.501422296841366, "rain_limit": 0.2, "temp_limit": 20}, {"sid": "C06", "name": "Uimastadion", "weekday": 2, "hour": 6, "label": "Wednesdy", "rain_bike_brought": 241.4426258172064, "no_rain_bike_brought": 38.08150483651713, "warm_bike_brought": 17.989310449699875, "cold_bike_brought": 53.15797351765447, "rain_bike_taken": 137.65168146257474, "no_rain_bike_taken": 28.657655334578422, "warm_bike_taken": 14.090539393343615, "cold_bike_taken": 37.206825423775676, "rain_limit": 0.2, "temp_limit": 20}, {"sid": "C06", "name": "Uimastadion", "weekday": 2, "hour": 7, "label": "Wednesdy", "rain_bike_brought": 165.10772191448063, "no_rain_bike_brought": 24.08017107387795, "warm_bike_brought": 8.11541194772386, "cold_bike_brought": 49.1839329101322, "rain_bike_taken": 157.26263977158615, "no_rain_bike_taken": 43.62214894145409, "warm_bike_taken": 22.26570280464442, "cold_bike_taken": 59.68328958166218, "rain_limit": 0.2, "temp_limit": 20}, {"sid": "C06", "name": "Uimastadion", "weekday": 2, "hour": 8, "label": "Wednesdy", "rain_bike_brought": 154.0778530759177, "no_rain_bike_brought": 35.83621412469459, "warm_bike_brought": 7.6399773265706985, "cold_bike_brought": 56.43924749243406, "rain_bike_taken": 183.72489355148304, "no_rain_bike_taken": 31.946360375588327, "warm_bike_taken": 14.943019605969024, "cold_bike_taken": 47.37478069052213, "rain_limit": 0.2, "temp_limit": 20}, {"sid": "C06", "name": "Uimastadion", "weekday": 2, "hour": 9, "label": "Wednesdy", "rain_bike_brought": 151.29415054302086, "no_rain_bike_brought": 29.40043754315791, "warm_bike_brought": 12.719276728030156, "cold_bike_brought": 64.45899230694982, "rain_bike_taken": 109.00520757155789, "no_rain_bike_taken": 24.269345291495824, "warm_bike_taken": 13.574376144919777, "cold_bike_taken": 55.39952648697072, "rain_limit": 0.2, "temp_limit": 20}, {"sid": "C06", "name": "Uimastadion", "weekday": 2, "hour": 10, "label": "Wednesdy", "rain_bike_brought": 151.22444790757493, "no_rain_bike_brought": 23.56694175042541, "warm_bike_brought": 9.502360657000573, "cold_bike_brought": 47.850159021997285, "rain_bike_taken": 91.97781295594015, "no_rain_bike_taken": 27.01040498451582, "warm_bike_taken": 10.514053873162254, "cold_bike_taken": 53.614925792119344, "rain_limit": 0.2, "temp_limit": 20}, {"sid": "C06", "name": "Uimastadion", "weekday": 2, "hour": 13, "label": "Wednesdy", "rain_bike_brought": 48.76636500566655, "no_rain_bike_brought": 11.289674988633577, "warm_bike_brought": 6.459051311689408, "cold_bike_brought": 21.903309922284055, "rain_bike_taken": 59.89231650134867, "no_rain_bike_taken": 15.829583867328864, "warm_bike_taken": 8.093067050046038, "cold_bike_taken": 30.18762265977509, "rain_limit": 0.2, "temp_limit": 20}, {"sid": "C06", "name": "Uimastadion", "weekday": 2, "hour": 14, "label": "Wednesdy", "rain_bike_brought": 19.22079523993433, "no_rain_bike_brought": 8.966223189422221, "warm_bike_brought": 4.796961155379772, "cold_bike_brought": 15.815580140429446, "rain_bike_taken": 27.05164502374757, "no_rain_bike_taken": 12.74862349999503, "warm_bike_taken": 5.907500146801379, "cold_bike_taken": 27.44847662368126, "rain_limit": 0.2, "temp_limit": 20}, {"sid": "C06", "name": "Uimastadion", "weekday": 2, "hour": 17, "label": "Wednesdy", "rain_bike_brought": 970.661875807814, "no_rain_bike_brought": 74.74043498891682, "warm_bike_brought": 61.32304310363175, "cold_bike_brought": 93.46156427191424, "rain_bike_taken": 791.4009935076584, "no_rain_bike_taken": 35.41340522086815, "warm_bike_taken": 42.254091145153055, "cold_bike_taken": 35.05377642346471, "rain_limit": 0.2, "temp_limit": 20}, {"sid": "C06", "name": "Uimastadion", "weekday": 2, "hour": 20, "label": "Wednesdy", "rain_bike_brought": 1144.1740617133653, "no_rain_bike_brought": 1233.7601577188295, "warm_bike_brought": 108.67198770990781, "cold_bike_brought": 1371.1532524855556, "rain_bike_taken": 1224.51272476535, "no_rain_bike_taken": 1016.1592151254978, "warm_bike_taken": 159.21855184049573, "cold_bike_taken": 1090.872076120943, "rain_limit": 0.2, "temp_limit": 20}, {"sid": "C06", "name": "Uimastadion", "weekday": 2, "hour": 21, "label": "Wednesdy", "rain_bike_brought": 939.8066153299375, "no_rain_bike_brought": 1344.9723804401158, "warm_bike_brought": 94.37980709422082, "cold_bike_brought": 1486.9535382530735, "rain_bike_taken": 1192.237307637898, "no_rain_bike_taken": 1334.5645664485073, "warm_bike_taken": 183.47781633899746, "cold_bike_taken": 1425.7594849275672, "rain_limit": 0.2, "temp_limit": 20}, {"sid": "C06", "name": "Uimastadion", "weekday": 2, "hour": 22, "label": "Wednesdy", "rain_bike_brought": 297.2541976866095, "no_rain_bike_brought": 1505.44640721626, "warm_bike_brought": 132.88886739586064, "cold_bike_brought": 1509.31322840583, "rain_bike_taken": 735.0087969537294, "no_rain_bike_taken": 1523.5580108978966, "warm_bike_taken": 194.1718570065273, "cold_bike_taken": 1520.1677289004238, "rain_limit": 0.2, "temp_limit": 20}, {"sid": "C06", "name": "Uimastadion", "weekday": 2, "hour": 23, "label": "Wednesdy", "rain_bike_brought": 1191.416780032507, "no_rain_bike_brought": 1572.6593898577485, "warm_bike_brought": 134.77132150613224, "cold_bike_brought": 1632.28219839656, "rain_bike_taken": 1364.9967703172006, "no_rain_bike_taken": 1598.4941497840312, "warm_bike_taken": 134.43928683963844, "cold_bike_taken": 1558.1571933950327, "rain_limit": 0.2, "temp_limit": 20}, {"sid": "C06", "name": "Uimastadion", "weekday": 3, "hour": 0, "label": "Thursday", "rain_bike_brought": 265.99643247268864, "no_rain_bike_brought": 242.73366418436882, "warm_bike_brought": 208.03778229670905, "cold_bike_brought": 247.11404112155523, "rain_bike_taken": 370.27444520024, "no_rain_bike_taken": 369.057184247877, "warm_bike_taken": 321.82481038386453, "cold_bike_taken": 375.40925936798595, "rain_limit": 0.2, "temp_limit": 20}, {"sid": "C06", "name": "Uimastadion", "weekday": 3, "hour": 1, "label": "Thursday", "rain_bike_brought": 161.27541570106905, "no_rain_bike_brought": 172.26613050015203, "warm_bike_brought": 138.8956866746579, "cold_bike_brought": 174.86331660193474, "rain_bike_taken": 236.7109520333051, "no_rain_bike_taken": 266.6146474739135, "warm_bike_taken": 238.30061328025178, "cold_bike_taken": 267.7905482243158, "rain_limit": 0.2, "temp_limit": 20}, {"sid": "C06", "name": "Uimastadion", "weekday": 3, "hour": 2, "label": "Thursday", "rain_bike_brought": 43.7143099934239, "no_rain_bike_brought": 138.2628317913707, "warm_bike_brought": 61.373208766806975, "cold_bike_brought": 138.4842906041692, "rain_bike_taken": 135.13192445752148, "no_rain_bike_taken": 212.26757839817606, "warm_bike_taken": 154.10925244801666, "cold_bike_taken": 212.87723352895856, "rain_limit": 0.2, "temp_limit": 20}, {"sid": "C06", "name": "Uimastadion", "weekday": 3, "hour": 3, "label": "Thursday", "rain_bike_brought": 72.21610915208151, "no_rain_bike_brought": 21.659360757976664, "warm_bike_brought": 9.883654410157268, "cold_bike_brought": 23.472805236444607, "rain_bike_taken": 91.0668089247964, "no_rain_bike_taken": 164.37907433124573, "warm_bike_taken": 72.79022837417996, "cold_bike_taken": 166.6476071551074, "rain_limit": 0.2, "temp_limit": 20}, {"sid": "C06", "name": "Uimastadion", "weekday": 3, "hour": 4, "label": "Thursday", "rain_bike_brought": 1193.2354349196419, "no_rain_bike_brought": 16.77126759503081, "warm_bike_brought": 9.88548098309957, "cold_bike_brought": 19.601681690618957, "rain_bike_taken": 756.3859612292804, "no_rain_bike_taken": 40.55175010429028, "warm_bike_taken": 17.747400312588955, "cold_bike_taken": 51.13817332349741, "rain_limit": 0.2, "temp_limit": 20}, {"sid": "C06", "name": "Uimastadion", "weekday": 3, "hour": 5, "label": "Thursday", "rain_bike_brought": 1111.78888956256, "no_rain_bike_brought": 36.263547522152116, "warm_bike_brought": 12.421356330112646, "cold_bike_brought": 45.364238497951504, "rain_bike_taken": 674.7466505760859, "no_rain_bike_taken": 14.18213801479558, "warm_bike_taken": 6.320694551140853, "cold_bike_taken": 17.611734553294276, "rain_limit": 0.2, "temp_limit": 20}, {"sid": "C06", "name": "Uimastadion", "weekday": 3, "hour": 6, "label": "Thursday", "rain_bike_brought": 74.749843035621, "no_rain_bike_brought": 35.57831897744999, "warm_bike_brought": 10.154866651070522, "cold_bike_brought": 54.06568676604609, "rain_bike_taken": 61.31763376048925, "no_rain_bike_taken": 25.730985437004108, "warm_bike_taken": 7.626865495435553, "cold_bike_taken": 37.65033430686708, "rain_limit": 0.2, "temp_limit": 20}, {"sid": "C06", "name": "Uimastadion", "weekday": 3, "hour": 7, "label": "Thursday", "rain_bike_brought": 88.598921835643, "no_rain_bike_brought": 25.585376595463355, "warm_bike_brought": 10.524979050697324, "cold_bike_brought": 40.762570228360374, "rain_bike_taken": 117.02486501263932, "no_rain_bike_taken": 39.70161626656855, "warm_bike_taken": 17.506703172860554, "cold_bike_taken": 54.86988718527816, "rain_limit": 0.2, "temp_limit": 20}, {"sid": "C06", "name": "Uimastadion", "weekday": 3, "hour": 8, "label": "Thursday", "rain_bike_brought": 48.39403799171325, "no_rain_bike_brought": 34.49858506563397, "warm_bike_brought": 6.461017971329411, "cold_bike_brought": 52.479363246002315, "rain_bike_taken": 115.49778328632044, "no_rain_bike_taken": 23.77178234402277, "warm_bike_taken": 9.55274735527333, "cold_bike_taken": 35.268742438750614, "rain_limit": 0.2, "temp_limit": 20}, {"sid": "C06", "name": "Uimastadion", "weekday": 3, "hour": 9, "label": "Thursday", "rain_bike_brought": 152.63299137179524, "no_rain_bike_brought": 23.330219458122844, "warm_bike_brought": 9.94153688754012, "cold_bike_brought": 49.17223517435258, "rain_bike_taken": 157.30247866250417, "no_rain_bike_taken": 28.900921730859746, "warm_bike_taken": 10.981654500216722, "cold_bike_taken": 57.51814809785334, "rain_limit": 0.2, "temp_limit": 20}, {"sid": "C06", "name": "Uimastadion", "weekday": 3, "hour": 10, "label": "Thursday", "rain_bike_brought": 695.2596303108486, "no_rain_bike_brought": 28.440272854250917, "warm_bike_brought": 11.13739859740454, "cold_bike_brought": 64.03992077335697, "rain_bike_taken": 257.2078394389678, "no_rain_bike_taken": 25.86586572226188, "warm_bike_taken": 11.837375220598588, "cold_bike_taken": 44.30367706274066, "rain_limit": 0.2, "temp_limit": 20}, {"sid": "C06", "name": "Uimastadion", "weekday": 3, "hour": 11, "label": "Thursday", "rain_bike_brought": 249.5387958876455, "no_rain_bike_brought": 27.601910368829174, "warm_bike_brought": 12.70537300034167, "cold_bike_brought": 57.90929654846176, "rain_bike_taken": 163.88905885146525, "no_rain_bike_taken": 21.454070283153357, "warm_bike_taken": 10.497568164712154, "cold_bike_taken": 50.887670527901214, "rain_limit": 0.2, "temp_limit": 20}, {"sid": "C06", "name": "Uimastadion", "weekday": 3, "hour": 12, "label": "Thursday", "rain_bike_brought": 86.46265884054876, "no_rain_bike_brought": 17.924630191173474, "warm_bike_brought": 9.952712638619728, "cold_bike_brought": 42.218747749923104, "rain_bike_taken": 92.53824967678256, "no_rain_bike_taken": 18.069275662856423, "warm_bike_taken": 10.0996426465521, "cold_bike_taken": 42.902471825254096, "rain_limit": 0.2, "temp_limit": 20}, {"sid": "C06", "name": "Uimastadion", "weekday": 3, "hour": 13, "label": "Thursday", "rain_bike_brought": 127.76700756172518, "no_rain_bike_brought": 16.202674747018825, "warm_bike_brought": 8.839736564338372, "cold_bike_brought": 33.95164160257394, "rain_bike_taken": 102.89615166523544, "no_rain_bike_taken": 16.23148319535513, "warm_bike_taken": 7.895498195573263, "cold_bike_taken": 32.30174425436872, "rain_limit": 0.2, "temp_limit": 20}, {"sid": "C06", "name": "Uimastadion", "weekday": 3, "hour": 14, "label": "Thursday", "rain_bike_brought": 46.80664402807152, "no_rain_bike_brought": 11.460735621557824, "warm_bike_brought": 6.089370692630117, "cold_bike_brought": 20.635873615530294, "rain_bike_taken": 152.01129081549493, "no_rain_bike_taken": 15.437524049540594, "warm_bike_taken": 8.244544273722818, "cold_bike_taken": 29.869924093067592, "rain_limit": 0.2, "temp_limit": 20}, {"sid": "C06", "name": "Uimastadion", "weekday": 3, "hour": 15, "label": "Thursday", "rain_bike_brought": 37.55965498215622, "no_rain_bike_brought": 13.82390562907649, "warm_bike_brought": 8.460665392887467, "cold_bike_brought": 21.63015474482712, "rain_bike_taken": 61.567323407031516, "no_rain_bike_taken": 11.914998556879809, "warm_bike_taken": 6.431550135280221, "cold_bike_taken": 22.080389735287685, "rain_limit": 0.2, "temp_limit": 20}, {"sid": "C06", "name": "Uimastadion", "weekday": 3, "hour": 16, "label": "Thursday", "rain_bike_brought": 65.43933023981884, "no_rain_bike_brought": 17.775845659449114, "warm_bike_brought": 9.60093822459292, "cold_bike_brought": 28.910789296223967, "rain_bike_taken": 40.16269450701377, "no_rain_bike_taken": 12.251791265747112, "warm_bike_taken": 6.874953992794459, "cold_bike_taken": 19.583664963170996, "rain_limit": 0.2, "temp_limit": 20}, {"sid": "C06", "name": "Uimastadion", "weekday": 3, "hour": 17, "label": "Thursday", "rain_bike_brought": 235.81410449579027, "no_rain_bike_brought": 143.70291262489675, "warm_bike_brought": 111.80558404534708, "cold_bike_brought": 222.0069543949524, "rain_bike_taken": 20.737406941401, "no_rain_bike_taken": 35.185449275692164, "warm_bike_taken": 44.86797210136738, "cold_bike_taken": 31.860712802604322, "rain_limit": 0.2, "temp_limit": 20}, {"sid": "C06", "name": "Uimastadion", "weekday": 3, "hour": 18, "label": "Thursday", "rain_bike_brought": 1166.236791048568, "no_rain_bike_brought": 262.6340081684048, "warm_bike_brought": 140.15269708947596, "cold_bike_brought": 416.52491323330713, "rain_bike_taken": 810.1846144843151, "no_rain_bike_taken": 223.13192764729368, "warm_bike_taken": 103.08114541966725, "cold_bike_taken": 498.5272112776858, "rain_limit": 0.2, "temp_limit": 20}, {"sid": "C06", "name": "Uimastadion", "weekday": 3, "hour": 19, "label": "Thursday", "rain_bike_brought": 1222.9822311012929, "no_rain_bike_brought": 575.0846981495407, "warm_bike_brought": 152.72307302275533, "cold_bike_brought": 654.5580143279095, "rain_bike_taken": 1201.2497122003765, "no_rain_bike_taken": 940.5815545049757, "warm_bike_taken": 220.57935423253932, "cold_bike_taken": 1119.4060309753256, "rain_limit": 0.2, "temp_limit": 20}, {"sid": "C06", "name": "Uimastadion", "weekday": 3, "hour": 20, "label": "Thursday", "rain_bike_brought": 1313.3169453144558, "no_rain_bike_brought": 935.1634493711866, "warm_bike_brought": 117.06158491483205, "cold_bike_brought": 1058.4680857966896, "rain_bike_taken": 1287.5514218439907, "no_rain_bike_taken": 1253.0480137788063, "warm_bike_taken": 186.15729106131255, "cold_bike_taken": 1388.4202890815634, "rain_limit": 0.2, "temp_limit": 20}, {"sid": "C06", "name": "Uimastadion", "weekday": 3, "hour": 21, "label": "Thursday", "rain_bike_brought": 1377.447647345296, "no_rain_bike_brought": 1287.8386016715108, "warm_bike_brought": 135.5127294845303, "cold_bike_brought": 1488.259551303135, "rain_bike_taken": 1306.854339209929, "no_rain_bike_taken": 1383.7805826092958, "warm_bike_taken": 183.90206161435444, "cold_bike_taken": 1487.2072621718432, "rain_limit": 0.2, "temp_limit": 20}, {"sid": "C06", "name": "Uimastadion", "weekday": 3, "hour": 22, "label": "Thursday", "rain_bike_brought": 1465.5046605783016, "no_rain_bike_brought": 1478.4937393436603, "warm_bike_brought": 325.65760348696324, "cold_bike_brought": 1558.6517710790774, "rain_bike_taken": 1380.1972016447944, "no_rain_bike_taken": 1509.227990202107, "warm_bike_taken": 228.12019953286944, "cold_bike_taken": 1490.5866750882537, "rain_limit": 0.2, "temp_limit": 20}, {"sid": "C06", "name": "Uimastadion", "weekday": 3, "hour": 23, "label": "Thursday", "rain_bike_brought": 1429.7301359050796, "no_rain_bike_brought": 1549.9984961659663, "warm_bike_brought": 304.4908717096428, "cold_bike_brought": 1626.6607829377106, "rain_bike_taken": 1468.5341285965196, "no_rain_bike_taken": 1599.777358205305, "warm_bike_taken": 1111.325591388855, "cold_bike_taken": 1565.4093119117676, "rain_limit": 0.2, "temp_limit": 20}, {"sid": "C06", "name": "Uimastadion", "weekday": 4, "hour": 0, "label": "Friday", "rain_bike_brought": 268.4785374675251, "no_rain_bike_brought": 305.5256463018217, "warm_bike_brought": 232.30776751443298, "cold_bike_brought": 310.73490877907165, "rain_bike_taken": 357.8140092315994, "no_rain_bike_taken": 438.5587257870064, "warm_bike_taken": 306.0965791761268, "cold_bike_taken": 445.44918155391196, "rain_limit": 0.2, "temp_limit": 20}, {"sid": "C06", "name": "Uimastadion", "weekday": 4, "hour": 1, "label": "Friday", "rain_bike_brought": 184.9886705384884, "no_rain_bike_brought": 159.82508225218018, "warm_bike_brought": 150.5394352063686, "cold_bike_brought": 165.47033313662828, "rain_bike_taken": 266.7935004830862, "no_rain_bike_taken": 298.3847990938989, "warm_bike_taken": 236.64719189650654, "cold_bike_taken": 303.51833688849, "rain_limit": 0.2, "temp_limit": 20}, {"sid": "C06", "name": "Uimastadion", "weekday": 4, "hour": 2, "label": "Friday", "rain_bike_brought": 143.00742577045875, "no_rain_bike_brought": 123.05320856548485, "warm_bike_brought": 100.01521192748638, "cold_bike_brought": 132.06919004828853, "rain_bike_taken": 186.6785510021374, "no_rain_bike_taken": 298.10883138044386, "warm_bike_taken": 153.77571604840443, "cold_bike_taken": 304.3837598140273, "rain_limit": 0.2, "temp_limit": 20}, {"sid": "C06", "name": "Uimastadion", "weekday": 4, "hour": 3, "label": "Friday", "rain_bike_brought": 28.57078793385741, "no_rain_bike_brought": 21.794886521384385, "warm_bike_brought": 14.190751822600351, "cold_bike_brought": 23.983775456794813, "rain_bike_taken": 133.6479165432072, "no_rain_bike_taken": 154.49952858164346, "warm_bike_taken": 74.52114203426932, "cold_bike_taken": 165.67122128129256, "rain_limit": 0.2, "temp_limit": 20}, {"sid": "C06", "name": "Uimastadion", "weekday": 4, "hour": 4, "label": "Friday", "rain_bike_brought": 206.08727941209307, "no_rain_bike_brought": 23.899195437964586, "warm_bike_brought": 17.84920666142282, "cold_bike_brought": 28.19466136609306, "rain_bike_taken": 192.5681367398406, "no_rain_bike_taken": 27.847054259605045, "warm_bike_taken": 19.86857829246785, "cold_bike_taken": 33.287360237567945, "rain_limit": 0.2, "temp_limit": 20}, {"sid": "C06", "name": "Uimastadion", "weekday": 4, "hour": 5, "label": "Friday", "rain_bike_brought": 78.142440386696, "no_rain_bike_brought": 30.39262283407791, "warm_bike_brought": 13.621536950011949, "cold_bike_brought": 40.25081546889907, "rain_bike_taken": 48.5562186326045, "no_rain_bike_taken": 20.411299920168922, "warm_bike_taken": 12.807619233872556, "cold_bike_taken": 23.95715354492823, "rain_limit": 0.2, "temp_limit": 20}, {"sid": "C06", "name": "Uimastadion", "weekday": 4, "hour": 6, "label": "Friday", "rain_bike_brought": 32.50101226773654, "no_rain_bike_brought": 46.09061473728229, "warm_bike_brought": 11.67541286552224, "cold_bike_brought": 64.2408634475092, "rain_bike_taken": 51.95471196837215, "no_rain_bike_taken": 44.98086238588324, "warm_bike_taken": 7.858679186412963, "cold_bike_taken": 59.93876354209613, "rain_limit": 0.2, "temp_limit": 20}, {"sid": "C06", "name": "Uimastadion", "weekday": 4, "hour": 7, "label": "Friday", "rain_bike_brought": 202.85451379694587, "no_rain_bike_brought": 37.35635439175329, "warm_bike_brought": 8.117428160101237, "cold_bike_brought": 63.5651789774265, "rain_bike_taken": 77.45877769944832, "no_rain_bike_taken": 53.14667300443915, "warm_bike_taken": 17.628969749353008, "cold_bike_taken": 79.17847177490707, "rain_limit": 0.2, "temp_limit": 20}, {"sid": "C06", "name": "Uimastadion", "weekday": 4, "hour": 8, "label": "Friday", "rain_bike_brought": 66.52895804218862, "no_rain_bike_brought": 33.67107604410497, "warm_bike_brought": 9.231850819131022, "cold_bike_brought": 43.81168161777189, "rain_bike_taken": 43.675078176082806, "no_rain_bike_taken": 32.35459538793176, "warm_bike_taken": 10.894705338402925, "cold_bike_taken": 45.21464331097217, "rain_limit": 0.2, "temp_limit": 20}, {"sid": "C06", "name": "Uimastadion", "weekday": 4, "hour": 9, "label": "Friday", "rain_bike_brought": 48.23030429478247, "no_rain_bike_brought": 25.768514167817006, "warm_bike_brought": 7.5920096016263345, "cold_bike_brought": 38.28944886408035, "rain_bike_taken": 75.32097199497751, "no_rain_bike_taken": 32.75288324622532, "warm_bike_taken": 10.424154979525387, "cold_bike_taken": 50.48375749949402, "rain_limit": 0.2, "temp_limit": 20}, {"sid": "C06", "name": "Uimastadion", "weekday": 4, "hour": 10, "label": "Friday", "rain_bike_brought": 49.476534377181366, "no_rain_bike_brought": 38.269722759667935, "warm_bike_brought": 19.06111049420259, "cold_bike_brought": 53.82565221450948, "rain_bike_taken": 76.50059554177702, "no_rain_bike_taken": 32.24288540266924, "warm_bike_taken": 10.672568596152571, "cold_bike_taken": 52.084292379546994, "rain_limit": 0.2, "temp_limit": 20}, {"sid": "C06", "name": "Uimastadion", "weekday": 4, "hour": 11, "label": "Friday", "rain_bike_brought": 613.719922109634, "no_rain_bike_brought": 33.27754835671482, "warm_bike_brought": 14.905453067383231, "cold_bike_brought": 57.35498432975298, "rain_bike_taken": 60.13008385760498, "no_rain_bike_taken": 28.595618027533288, "warm_bike_taken": 13.878248202137964, "cold_bike_taken": 41.624781027703705, "rain_limit": 0.2, "temp_limit": 20}, {"sid": "C06", "name": "Uimastadion", "weekday": 4, "hour": 12, "label": "Friday", "rain_bike_brought": 529.2356956043336, "no_rain_bike_brought": 31.518495232403684, "warm_bike_brought": 14.121617480824156, "cold_bike_brought": 57.40038130464666, "rain_bike_taken": 573.6672283962351, "no_rain_bike_taken": 28.20387330031406, "warm_bike_taken": 12.881261074762307, "cold_bike_taken": 54.5825111309034, "rain_limit": 0.2, "temp_limit": 20}, {"sid": "C06", "name": "Uimastadion", "weekday": 4, "hour": 13, "label": "Friday", "rain_bike_brought": 36.1207303380204, "no_rain_bike_brought": 18.628070240074024, "warm_bike_brought": 9.863619292200367, "cold_bike_brought": 31.593533747277363, "rain_bike_taken": 47.500323729216284, "no_rain_bike_taken": 22.76059920489211, "warm_bike_taken": 13.184297521292743, "cold_bike_taken": 33.65257494497172, "rain_limit": 0.2, "temp_limit": 20}, {"sid": "C06", "name": "Uimastadion", "weekday": 4, "hour": 14, "label": "Friday", "rain_bike_brought": 98.74310141150487, "no_rain_bike_brought": 20.546938268661407, "warm_bike_brought": 11.696408768393951, "cold_bike_brought": 42.40440705327732, "rain_bike_taken": 75.25341925648452, "no_rain_bike_taken": 20.9780486568146, "warm_bike_taken": 10.111194898028488, "cold_bike_taken": 36.99231451626955, "rain_limit": 0.2, "temp_limit": 20}, {"sid": "C06", "name": "Uimastadion", "weekday": 4, "hour": 15, "label": "Friday", "rain_bike_brought": 108.22836969274336, "no_rain_bike_brought": 23.79133863567149, "warm_bike_brought": 11.449903015870692, "cold_bike_brought": 42.06487741796312, "rain_bike_taken": 74.17510277280775, "no_rain_bike_taken": 20.63070944477813, "warm_bike_taken": 10.982248703697204, "cold_bike_taken": 38.466507916617914, "rain_limit": 0.2, "temp_limit": 20}, {"sid": "C06", "name": "Uimastadion", "weekday": 5, "hour": 2, "label": "Saturday", "rain_bike_brought": 237.83607980282284, "no_rain_bike_brought": 235.22603661377, "warm_bike_brought": 72.18440699327329, "cold_bike_brought": 249.26398118451635, "rain_bike_taken": 482.577071101275, "no_rain_bike_taken": 400.1592589931989, "warm_bike_taken": 86.20155350096931, "cold_bike_taken": 378.47774877269325, "rain_limit": 0.2, "temp_limit": 20}, {"sid": "C06", "name": "Uimastadion", "weekday": 5, "hour": 3, "label": "Saturday", "rain_bike_brought": 142.19790224072588, "no_rain_bike_brought": 98.68387243507854, "warm_bike_brought": 69.7685423145236, "cold_bike_brought": 105.56815713245877, "rain_bike_taken": 490.9862145610547, "no_rain_bike_taken": 320.4928644041503, "warm_bike_taken": 77.47946445711268, "cold_bike_taken": 327.53639472618335, "rain_limit": 0.2, "temp_limit": 20}, {"sid": "C06", "name": "Uimastadion", "weekday": 5, "hour": 4, "label": "Saturday", "rain_bike_brought": 58.074405805993585, "no_rain_bike_brought": 92.79647981693122, "warm_bike_brought": 97.70316421552351, "cold_bike_brought": 92.62584085044301, "rain_bike_taken": 304.5571322582551, "no_rain_bike_taken": 172.78236342403693, "warm_bike_taken": 86.98528009765667, "cold_bike_taken": 193.1688706631408, "rain_limit": 0.2, "temp_limit": 20}, {"sid": "C06", "name": "Uimastadion", "weekday": 5, "hour": 5, "label": "Saturday", "rain_bike_brought": 81.16420331410418, "no_rain_bike_brought": 61.35918484048838, "warm_bike_brought": 33.50904552607307, "cold_bike_brought": 76.65170484150067, "rain_bike_taken": 220.61479020274038, "no_rain_bike_taken": 107.60733355530603, "warm_bike_taken": 43.99656640708803, "cold_bike_taken": 153.9158744831937, "rain_limit": 0.2, "temp_limit": 20}, {"sid": "C06", "name": "Uimastadion", "weekday": 5, "hour": 6, "label": "Saturday", "rain_bike_brought": 56.36778965027093, "no_rain_bike_brought": 29.641254164365, "warm_bike_brought": 11.796969411266277, "cold_bike_brought": 48.93158162670984, "rain_bike_taken": 129.1959395120518, "no_rain_bike_taken": 81.88718675791159, "warm_bike_taken": 34.279315128912934, "cold_bike_taken": 133.6263760720228, "rain_limit": 0.2, "temp_limit": 20}, {"sid": "C06", "name": "Uimastadion", "weekday": 5, "hour": 7, "label": "Saturday", "rain_bike_brought": 69.89053645046646, "no_rain_bike_brought": 27.866854109154634, "warm_bike_brought": 11.742343421145192, "cold_bike_brought": 39.734404481196776, "rain_bike_taken": 69.21191097297124, "no_rain_bike_taken": 44.13151379218174, "warm_bike_taken": 19.44577246911229, "cold_bike_taken": 73.38463605198204, "rain_limit": 0.2, "temp_limit": 20}, {"sid": "C06", "name": "Uimastadion", "weekday": 5, "hour": 8, "label": "Saturday", "rain_bike_brought": 236.43526000320057, "no_rain_bike_brought": 18.40781876505818, "warm_bike_brought": 10.146501005993041, "cold_bike_brought": 30.949376677542425, "rain_bike_taken": 289.32181003515734, "no_rain_bike_taken": 24.536505883260187, "warm_bike_taken": 17.189923599574634, "cold_bike_taken": 39.20381910934756, "rain_limit": 0.2, "temp_limit": 20}, {"sid": "C06", "name": "Uimastadion", "weekday": 5, "hour": 9, "label": "Saturday", "rain_bike_brought": 134.47175030562994, "no_rain_bike_brought": 13.579970014162383, "warm_bike_brought": 8.927860449931531, "cold_bike_brought": 24.513892517004543, "rain_bike_taken": 186.605856850677, "no_rain_bike_taken": 16.945477678894456, "warm_bike_taken": 12.000507065135789, "cold_bike_taken": 29.152969082873142, "rain_limit": 0.2, "temp_limit": 20}, {"sid": "C06", "name": "Uimastadion", "weekday": 5, "hour": 10, "label": "Saturday", "rain_bike_brought": 180.37278841172503, "no_rain_bike_brought": 16.59975921983227, "warm_bike_brought": 11.551482498938423, "cold_bike_brought": 26.94977871899221, "rain_bike_taken": 210.95406519005203, "no_rain_bike_taken": 15.329539927976153, "warm_bike_taken": 8.612365126555915, "cold_bike_taken": 30.458850288531533, "rain_limit": 0.2, "temp_limit": 20}, {"sid": "C06", "name": "Uimastadion", "weekday": 5, "hour": 11, "label": "Saturday", "rain_bike_brought": 612.4080702735578, "no_rain_bike_brought": 23.116606590058733, "warm_bike_brought": 14.402920802051971, "cold_bike_brought": 39.11576642951121, "rain_bike_taken": 656.7525677953712, "no_rain_bike_taken": 15.452504080567858, "warm_bike_taken": 9.53051164930673, "cold_bike_taken": 22.91230264047548, "rain_limit": 0.2, "temp_limit": 20}, {"sid": "C06", "name": "Uimastadion", "weekday": 5, "hour": 12, "label": "Saturday", "rain_bike_brought": 345.8945930691395, "no_rain_bike_brought": 31.481909020933028, "warm_bike_brought": 21.310665878120037, "cold_bike_brought": 48.74606869405497, "rain_bike_taken": 358.1372436546775, "no_rain_bike_taken": 16.957766185637535, "warm_bike_taken": 11.514752459248275, "cold_bike_taken": 27.78458761900924, "rain_limit": 0.2, "temp_limit": 20}, {"sid": "C06", "name": "Uimastadion", "weekday": 5, "hour": 13, "label": "Saturday", "rain_bike_brought": 445.50965074787194, "no_rain_bike_brought": 40.48298861965054, "warm_bike_brought": 22.187137495631614, "cold_bike_brought": 52.45312241850054, "rain_bike_taken": 489.9991537397739, "no_rain_bike_taken": 31.235428930939808, "warm_bike_taken": 20.318358633086643, "cold_bike_taken": 39.522666912338956, "rain_limit": 0.2, "temp_limit": 20}, {"sid": "C06", "name": "Uimastadion", "weekday": 5, "hour": 14, "label": "Saturday", "rain_bike_brought": 138.6181156144935, "no_rain_bike_brought": 28.110679692669212, "warm_bike_brought": 20.146463377547057, "cold_bike_brought": 38.23273947070067, "rain_bike_taken": 235.48570500589176, "no_rain_bike_taken": 26.672930687661243, "warm_bike_taken": 17.82557354533187, "cold_bike_taken": 40.850458134259256, "rain_limit": 0.2, "temp_limit": 20}, {"sid": "C06", "name": "Uimastadion", "weekday": 5, "hour": 15, "label": "Saturday", "rain_bike_brought": 105.73711155123056, "no_rain_bike_brought": 28.947964668452702, "warm_bike_brought": 20.537144404615805, "cold_bike_brought": 42.38783489571956, "rain_bike_taken": 55.481925646667435, "no_rain_bike_taken": 26.624593269252603, "warm_bike_taken": 23.656440761914876, "cold_bike_taken": 30.25857062848558, "rain_limit": 0.2, "temp_limit": 20}, {"sid": "C06", "name": "Uimastadion", "weekday": 5, "hour": 16, "label": "Saturday", "rain_bike_brought": 283.678943270632, "no_rain_bike_brought": 38.017115844336594, "warm_bike_brought": 23.282371787182903, "cold_bike_brought": 62.239659937511945, "rain_bike_taken": 352.67576434427286, "no_rain_bike_taken": 33.67717157874915, "warm_bike_taken": 27.703415485402875, "cold_bike_taken": 40.45604350716871, "rain_limit": 0.2, "temp_limit": 20}, {"sid": "C06", "name": "Uimastadion", "weekday": 5, "hour": 17, "label": "Saturday", "rain_bike_brought": 115.30435126660954, "no_rain_bike_brought": 117.17462941498746, "warm_bike_brought": 55.62920140055474, "cold_bike_brought": 234.13132387133643, "rain_bike_taken": 98.84407203735594, "no_rain_bike_taken": 47.321596658475386, "warm_bike_taken": 37.00243813277698, "cold_bike_taken": 61.66951756473564, "rain_limit": 0.2, "temp_limit": 20}, {"sid": "C06", "name": "Uimastadion", "weekday": 5, "hour": 18, "label": "Saturday", "rain_bike_brought": 89.63647665057786, "no_rain_bike_brought": 195.29556348990374, "warm_bike_brought": 63.02596130674003, "cold_bike_brought": 336.5834220321565, "rain_bike_taken": 86.40431965829343, "no_rain_bike_taken": 198.3485854410383, "warm_bike_taken": 75.00306213282957, "cold_bike_taken": 365.70921619930317, "rain_limit": 0.2, "temp_limit": 20}, {"sid": "C06", "name": "Uimastadion", "weekday": 5, "hour": 19, "label": "Saturday", "rain_bike_brought": 172.85035573069743, "no_rain_bike_brought": 606.0379234556411, "warm_bike_brought": 222.54409944691372, "cold_bike_brought": 716.1174591383719, "rain_bike_taken": 156.60726955506036, "no_rain_bike_taken": 462.3409130907688, "warm_bike_taken": 257.0748412290045, "cold_bike_taken": 540.637326978102, "rain_limit": 0.2, "temp_limit": 20}, {"sid": "C06", "name": "Uimastadion", "weekday": 5, "hour": 20, "label": "Saturday", "rain_bike_brought": 545.6919275252644, "no_rain_bike_brought": 632.8286091180422, "warm_bike_brought": 128.0721732826664, "cold_bike_brought": 725.3395634342544, "rain_bike_taken": 311.90896075158304, "no_rain_bike_taken": 625.3093805102856, "warm_bike_taken": 209.0147832505685, "cold_bike_taken": 648.7577031987449, "rain_limit": 0.2, "temp_limit": 20}, {"sid": "C06", "name": "Uimastadion", "weekday": 5, "hour": 21, "label": "Saturday", "rain_bike_brought": 222.50998651881608, "no_rain_bike_brought": 974.8373178119328, "warm_bike_brought": 1413.3417482411003, "cold_bike_brought": 886.76606730192, "rain_bike_taken": 180.71554809209857, "no_rain_bike_taken": 768.1271522344197, "warm_bike_taken": 110.17300615906433, "cold_bike_taken": 770.2316941590069, "rain_limit": 0.2, "temp_limit": 20}, {"sid": "C06", "name": "Uimastadion", "weekday": 5, "hour": 22, "label": "Saturday", "rain_bike_brought": 640.3261076248366, "no_rain_bike_brought": 1055.4809787011864, "warm_bike_brought": 1468.9765759212164, "cold_bike_brought": 1084.6072384234249, "rain_bike_taken": 183.18257066559056, "no_rain_bike_taken": 1163.4371773718572, "warm_bike_taken": 1318.2201275662326, "cold_bike_taken": 1091.5604725197334, "rain_limit": 0.2, "temp_limit": 20}, {"sid": "C06", "name": "Uimastadion", "weekday": 5, "hour": 23, "label": "Saturday", "rain_bike_brought": 606.7127679569963, "no_rain_bike_brought": 1346.4482370812007, "warm_bike_brought": 1474.8748419751585, "cold_bike_brought": 1392.6496466612884, "rain_bike_taken": 584.8898912539796, "no_rain_bike_taken": 1360.1007580243956, "warm_bike_taken": 1419.712122748372, "cold_bike_taken": 1398.3882939148973, "rain_limit": 0.2, "temp_limit": 20}, {"sid": "C06", "name": "Uimastadion", "weekday": 6, "hour": 0, "label": "Sunday", "rain_bike_brought": 1291.1905511856055, "no_rain_bike_brought": 631.8233257493463, "warm_bike_brought": 436.1914736797, "cold_bike_brought": 657.0962099850298, "rain_bike_taken": 1307.849714731307, "no_rain_bike_taken": 810.3315454080301, "warm_bike_taken": 491.7336471654474, "cold_bike_taken": 837.9515662944806, "rain_limit": 0.2, "temp_limit": 20}, {"sid": "C06", "name": "Uimastadion", "weekday": 6, "hour": 1, "label": "Sunday", "rain_bike_brought": 1185.3571534753246, "no_rain_bike_brought": 486.4868169076865, "warm_bike_brought": 352.7183974923468, "cold_bike_brought": 501.6025382914446, "rain_bike_taken": 1202.9624747138896, "no_rain_bike_taken": 686.0499317263251, "warm_bike_taken": 408.35348593613395, "cold_bike_taken": 707.2025247763098, "rain_limit": 0.2, "temp_limit": 20}, {"sid": "C06", "name": "Uimastadion", "weekday": 6, "hour": 2, "label": "Sunday", "rain_bike_brought": 1209.1821919621548, "no_rain_bike_brought": 350.8021496296314, "warm_bike_brought": 270.33640648373887, "cold_bike_brought": 361.0803631058744, "rain_bike_taken": 1234.8675926594922, "no_rain_bike_taken": 528.350343948455, "warm_bike_taken": 326.0633872429745, "cold_bike_taken": 548.8599334341013, "rain_limit": 0.2, "temp_limit": 20}, {"sid": "C06", "name": "Uimastadion", "weekday": 6, "hour": 3, "label": "Sunday", "rain_bike_brought": 578.0982076209389, "no_rain_bike_brought": 259.9905988907864, "warm_bike_brought": 110.18241818956291, "cold_bike_brought": 295.1666019949901, "rain_bike_taken": 693.676659293313, "no_rain_bike_taken": 342.653665609652, "warm_bike_taken": 278.65531095279056, "cold_bike_taken": 359.7656979706037, "rain_limit": 0.2, "temp_limit": 20}, {"sid": "C06", "name": "Uimastadion", "weekday": 6, "hour": 4, "label": "Sunday", "rain_bike_brought": 852.0133727836858, "no_rain_bike_brought": 215.9458034850555, "warm_bike_brought": 98.72331796474161, "cold_bike_brought": 230.09905326438803, "rain_bike_taken": 858.2557184689832, "no_rain_bike_taken": 342.5921301157472, "warm_bike_taken": 195.81365219080504, "cold_bike_taken": 353.44147740421255, "rain_limit": 0.2, "temp_limit": 20}, {"sid": "C06", "name": "Uimastadion", "weekday": 6, "hour": 5, "label": "Sunday", "rain_bike_brought": 1107.0310582948, "no_rain_bike_brought": 75.69018273779875, "warm_bike_brought": 44.06927271460855, "cold_bike_brought": 81.57851657302128, "rain_bike_taken": 1151.4197711758316, "no_rain_bike_taken": 240.84599216656355, "warm_bike_taken": 130.9390619697942, "cold_bike_taken": 249.99003643202246, "rain_limit": 0.2, "temp_limit": 20}, {"sid": "C06", "name": "Uimastadion", "weekday": 6, "hour": 6, "label": "Sunday", "rain_bike_brought": 1024.215880963014, "no_rain_bike_brought": 34.93437327905574, "warm_bike_brought": 16.331049582198954, "cold_bike_brought": 41.45707142107253, "rain_bike_taken": 1068.5666306112805, "no_rain_bike_taken": 119.53613662379684, "warm_bike_taken": 72.45608906024087, "cold_bike_taken": 134.70915367101188, "rain_limit": 0.2, "temp_limit": 20}, {"sid": "C06", "name": "Uimastadion", "weekday": 6, "hour": 7, "label": "Sunday", "rain_bike_brought": 524.0902569796795, "no_rain_bike_brought": 30.346264497503494, "warm_bike_brought": 22.06299109861306, "cold_bike_brought": 33.94141166922894, "rain_bike_taken": 525.4785597956056, "no_rain_bike_taken": 47.21061949199688, "warm_bike_taken": 23.477977226807198, "cold_bike_taken": 58.801518377080875, "rain_limit": 0.2, "temp_limit": 20}, {"sid": "C06", "name": "Uimastadion", "weekday": 6, "hour": 8, "label": "Sunday", "rain_bike_brought": 442.5556190286794, "no_rain_bike_brought": 21.26196274167356, "warm_bike_brought": 9.757804472668848, "cold_bike_brought": 29.87529821822389, "rain_bike_taken": 443.95131266704976, "no_rain_bike_taken": 32.05937909845383, "warm_bike_taken": 31.63435591704196, "cold_bike_taken": 33.708244261041244, "rain_limit": 0.2, "temp_limit": 20}, {"sid": "C06", "name": "Uimastadion", "weekday": 6, "hour": 9, "label": "Sunday", "rain_bike_brought": 777.8273349750713, "no_rain_bike_brought": 16.824149329875006, "warm_bike_brought": 10.747809583635313, "cold_bike_brought": 22.884919362154722, "rain_bike_taken": 822.2282210550928, "no_rain_bike_taken": 21.101501753190423, "warm_bike_taken": 12.572981218174737, "cold_bike_taken": 28.611120738211458, "rain_limit": 0.2, "temp_limit": 20}, {"sid": "C06", "name": "Uimastadion", "weekday": 6, "hour": 10, "label": "Sunday", "rain_bike_brought": 385.1133411481626, "no_rain_bike_brought": 16.351378750352104, "warm_bike_brought": 9.102385357530945, "cold_bike_brought": 25.149395233718955, "rain_bike_taken": 389.79232740255526, "no_rain_bike_taken": 16.625560770919286, "warm_bike_taken": 10.613117517862097, "cold_bike_taken": 24.634045638545377, "rain_limit": 0.2, "temp_limit": 20}, {"sid": "C06", "name": "Uimastadion", "weekday": 6, "hour": 11, "label": "Sunday", "rain_bike_brought": 284.1387044489157, "no_rain_bike_brought": 13.796561097572974, "warm_bike_brought": 10.893941352139471, "cold_bike_brought": 18.55958634830907, "rain_bike_taken": 283.88786357598445, "no_rain_bike_taken": 15.038280220136011, "warm_bike_taken": 10.43232709598146, "cold_bike_taken": 21.180224126881434, "rain_limit": 0.2, "temp_limit": 20}, {"sid": "C06", "name": "Uimastadion", "weekday": 6, "hour": 12, "label": "Sunday", "rain_bike_brought": 163.57381863620344, "no_rain_bike_brought": 16.086309912174052, "warm_bike_brought": 10.517250828803373, "cold_bike_brought": 24.935614850920317, "rain_bike_taken": 150.13567982230458, "no_rain_bike_taken": 15.281263215083849, "warm_bike_taken": 8.801911462057223, "cold_bike_taken": 24.878447157094907, "rain_limit": 0.2, "temp_limit": 20}, {"sid": "C06", "name": "Uimastadion", "weekday": 6, "hour": 13, "label": "Sunday", "rain_bike_brought": 158.1979399990198, "no_rain_bike_brought": 22.814343378923397, "warm_bike_brought": 13.219656436842824, "cold_bike_brought": 32.723749955081374, "rain_bike_taken": 145.11965173564622, "no_rain_bike_taken": 15.811724636479811, "warm_bike_taken": 11.339131585417508, "cold_bike_taken": 20.176071012675447, "rain_limit": 0.2, "temp_limit": 20}, {"sid": "C06", "name": "Uimastadion", "weekday": 6, "hour": 14, "label": "Sunday", "rain_bike_brought": 185.96238014900348, "no_rain_bike_brought": 20.7847488587574, "warm_bike_brought": 12.831725415294203, "cold_bike_brought": 31.650923120213424, "rain_bike_taken": 152.5527703046536, "no_rain_bike_taken": 19.61079046246608, "warm_bike_taken": 13.364432449319402, "cold_bike_taken": 27.37981280162581, "rain_limit": 0.2, "temp_limit": 20}, {"sid": "C06", "name": "Uimastadion", "weekday": 6, "hour": 15, "label": "Sunday", "rain_bike_brought": 41.6788285118389, "no_rain_bike_brought": 18.028212859229544, "warm_bike_brought": 9.723222532029192, "cold_bike_brought": 24.496439741699582, "rain_bike_taken": 58.55711204689902, "no_rain_bike_taken": 16.73264573003296, "warm_bike_taken": 9.374706060248174, "cold_bike_taken": 22.352945020531575, "rain_limit": 0.2, "temp_limit": 20}, {"sid": "C06", "name": "Uimastadion", "weekday": 6, "hour": 16, "label": "Sunday", "rain_bike_brought": 56.52571874826433, "no_rain_bike_brought": 19.914475346975443, "warm_bike_brought": 12.131860132716302, "cold_bike_brought": 26.57114399431493, "rain_bike_taken": 39.21296526423173, "no_rain_bike_taken": 17.236510047162266, "warm_bike_taken": 9.785552391936877, "cold_bike_taken": 22.383307795309047, "rain_limit": 0.2, "temp_limit": 20}, {"sid": "C06", "name": "Uimastadion", "weekday": 6, "hour": 17, "label": "Sunday", "rain_bike_brought": 134.3230171168247, "no_rain_bike_brought": 91.55638727671928, "warm_bike_brought": 133.3930672015829, "cold_bike_brought": 86.1348683903852, "rain_bike_taken": 54.899710854833984, "no_rain_bike_taken": 50.31698482465553, "warm_bike_taken": 87.22311314211078, "cold_bike_taken": 43.57538179477597, "rain_limit": 0.2, "temp_limit": 20}, {"sid": "C06", "name": "Uimastadion", "weekday": 6, "hour": 18, "label": "Sunday", "rain_bike_brought": 128.381214829288, "no_rain_bike_brought": 443.4305481189891, "warm_bike_brought": 150.48731135424913, "cold_bike_brought": 490.93027893327655, "rain_bike_taken": 133.77363768572678, "no_rain_bike_taken": 283.00733238753736, "warm_bike_taken": 149.87266347868626, "cold_bike_taken": 281.9389699443498, "rain_limit": 0.2, "temp_limit": 20}, {"sid": "C06", "name": "Uimastadion", "weekday": 6, "hour": 20, "label": "Sunday", "rain_bike_brought": 1021.7778049401271, "no_rain_bike_brought": 1267.8415760965966, "warm_bike_brought": 246.89132794391202, "cold_bike_brought": 1317.2376191703158, "rain_bike_taken": 943.8363026727058, "no_rain_bike_taken": 1172.6929614520236, "warm_bike_taken": 251.68654616459978, "cold_bike_taken": 1212.173043895746, "rain_limit": 0.2, "temp_limit": 20}, {"sid": "C06", "name": "Uimastadion", "weekday": 6, "hour": 22, "label": "Sunday", "rain_bike_brought": 1567.3909189747678, "no_rain_bike_brought": 1556.1051195732584, "warm_bike_brought": 1589.7317974056173, "cold_bike_brought": 1544.6534199052571, "rain_bike_taken": 1496.1893347224204, "no_rain_bike_taken": 1477.3870667114904, "warm_bike_taken": 1504.3310082473101, "cold_bike_taken": 1471.8208559664856, "rain_limit": 0.2, "temp_limit": 20}, {"sid": "C06", "name": "Uimastadion", "weekday": 6, "hour": 23, "label": "Sunday", "rain_bike_brought": 1666.3395830234754, "no_rain_bike_brought": 1627.886411580167, "warm_bike_brought": 1672.3340861481997, "cold_bike_brought": 1615.907516506842, "rain_bike_taken": 1595.7948787787802, "no_rain_bike_taken": 1552.7890789414382, "warm_bike_taken": 1587.1852048364565, "cold_bike_taken": 1546.6262428305338, "rain_limit": 0.2, "temp_limit": 20}]